{
    "authorName": "F. Porto",
    "openalexAuthorId": "A5011827798",
    "name": "F. Porto",
    "url": "https://openalex.org/A5011827798",
    "affiliations": [
        {
            "name": "Centro Siciliano di Fisica Nucleare e di Struttura della Materia",
            "years": [
                1969,
                1983,
                2009
            ]
        },
        {
            "name": "University of Catania",
            "years": [
                1981,
                1982,
                1983,
                1996,
                1998,
                1999,
                2000,
                2002,
                2003,
                2004,
                2005,
                2008,
                2009,
                2010,
                2011,
                2012,
                2013,
                2014,
                2015,
                2020
            ]
        },
        {
            "name": "Istituti di Ricovero e Cura a Carattere Scientifico",
            "years": [
                1981,
                1982
            ]
        },
        {
            "name": "Istituto Nazionale di Fisica Nucleare, Sezione di Catania",
            "years": [
                1983,
                2007,
                2009
            ]
        },
        {
            "name": "Istituto Nazionale di Fisica Nucleare, Laboratori Nazionali del Sud",
            "years": [
                1983,
                1998,
                1999,
                2002,
                2005,
                2006,
                2007,
                2008,
                2009,
                2010,
                2011,
                2012,
                2013,
                2014,
                2015
            ]
        },
        {
            "name": "Istituto Nazionale di Fisica Nucleare",
            "years": [
                1996,
                1998,
                2005,
                2010
            ]
        },
        {
            "name": "University of Messina",
            "years": [
                2009
            ]
        },
        {
            "name": "Saha Institute of Nuclear Physics",
            "years": [
                2009
            ]
        },
        {
            "name": "Università degli Studi di Enna Kore",
            "years": [
                2009
            ]
        },
        {
            "name": "University of Silesia in Katowice",
            "years": [
                2009
            ]
        },
        {
            "name": "Universidade de Uberaba",
            "years": [
                2015,
                2017,
                2018,
                2023
            ]
        },
        {
            "name": "Universidade Federal do Triângulo Mineiro",
            "years": [
                2019
            ]
        },
        {
            "name": "Sabin Vaccine Institute",
            "years": [
                2023
            ]
        },
        {
            "name": "Universidade Federal de Uberlândia",
            "years": [
                2023,
                2025
            ]
        }
    ]
}