{
    "paperId": "3c2dac02df2c000f2ceffc7c05a8de1996d7763e",
    "title": "Regional-Scale Dispersion and Concentration Prediction of Emerging Pollutants: From Mechanistic Models to Intelligent Algorithms",
    "year": 2025,
    "venue": "Advances in Environmental Protection",
    "authors": [
        "美凤 陈"
    ],
    "doi": "10.12677/aep.2025.159135",
    "arxivId": null,
    "url": "https://www.semanticscholar.org/paper/3c2dac02df2c000f2ceffc7c05a8de1996d7763e",
    "isOpenAccess": false,
    "openAccessPdf": "",
    "publicationTypes": [
        "JournalArticle"
    ],
    "s2FieldsOfStudy": [
        {
            "category": "Environmental Science",
            "source": "s2-fos-model"
        },
        {
            "category": "Computer Science",
            "source": "s2-fos-model"
        }
    ],
    "abstract": null,
    "citationCount": 0,
    "referenceCount": 79
}