{
    "paperId": "52cb844b5f4ec34cf0e21f87a4dffc6b8a9e4403",
    "title": "Lessons learned and recommendations for data coordination in collaborative research: The CSER consortium experience",
    "year": 2022,
    "venue": "HGG advances",
    "authors": [
        "Kathleen Muenzen",
        "L. Amendola",
        "T. Kauffman",
        "Kathleen F. Mittendorf",
        "J. Bensen",
        "Flavia Chen",
        "Richard Green",
        "B. Powell",
        "M. Kvale",
        "Frank A Angelo",
        "L. Farnan",
        "Stephanie M. Fullerton",
        "J. Robinson",
        "Tianran Li",
        "Priyanka Murali",
        "J. Lawlor",
        "Jeffrey Ou",
        "L. Hindorff",
        "G. Jarvik",
        "D. Crosslin"
    ],
    "doi": "10.1016/j.xhgg.2022.100120",
    "arxivId": null,
    "url": "https://www.semanticscholar.org/paper/52cb844b5f4ec34cf0e21f87a4dffc6b8a9e4403",
    "isOpenAccess": true,
    "openAccessPdf": "https://doi.org/10.1016/j.xhgg.2022.100120",
    "publicationTypes": [
        "JournalArticle",
        "Review"
    ],
    "s2FieldsOfStudy": [
        {
            "category": "Medicine",
            "source": "external"
        },
        {
            "category": "Medicine",
            "source": "s2-fos-model"
        },
        {
            "category": "Computer Science",
            "source": "s2-fos-model"
        }
    ],
    "abstract": null,
    "citationCount": 5,
    "referenceCount": 52
}