{
    "paperId": "b1b63f8d1d27033a78c7ba81e6d2d0cb47dbb6c1",
    "title": "Machine learning in demand planning: Cross-industry overview",
    "year": 2019,
    "venue": "",
    "authors": [
        "N. Moroff",
        "S. Sardesai"
    ],
    "doi": "10.15480/882.2476",
    "arxivId": null,
    "url": "https://www.semanticscholar.org/paper/b1b63f8d1d27033a78c7ba81e6d2d0cb47dbb6c1",
    "isOpenAccess": false,
    "openAccessPdf": "",
    "publicationTypes": [
        "Review"
    ],
    "s2FieldsOfStudy": [
        {
            "category": "Computer Science",
            "source": "external"
        },
        {
            "category": "Computer Science",
            "source": "s2-fos-model"
        },
        {
            "category": "Business",
            "source": "s2-fos-model"
        },
        {
            "category": "Engineering",
            "source": "s2-fos-model"
        }
    ],
    "abstract": null,
    "citationCount": 3,
    "referenceCount": 60
}